{
  "project_info": {
    "project_number": "490283506799",
    "firebase_url": "https://findapro-a11a2.firebaseio.com",
    "project_id": "findapro-a11a2",
    "storage_bucket": "findapro-a11a2.appspot.com"
  },
  "client": [
    {
      "client_info": {
        "mobilesdk_app_id": "1:490283506799:android:2c1ff2167a6380c548419a",
        "android_client_info": {
          "package_name": "com.julien.findapro"
        }
      },
      "oauth_client": [
        {
          "client_id": "490283506799-1s7l9khm9onlsh7tao0hstop93d71goo.apps.googleusercontent.com",
          "client_type": 1,
          "android_info": {
            "package_name": "com.julien.findapro",
            "certificate_hash": "104e2575c7a8bdaa2a89f9381269ed1c5f61cad9"
          }
        },
        {
          "client_id": "490283506799-29rjdterm0rds4acka4p85pb0pk053oa.apps.googleusercontent.com",
          "client_type": 3
        }
      ],
      "api_key": [
        {
          "current_key": "AIzaSyBoHNUeXhZJiNVRT_d5t-qDlUVF6dqobw0"
        }
      ],
      "services": {
        "appinvite_service": {
          "other_platform_oauth_client": [
            {
              "client_id": "490283506799-29rjdterm0rds4acka4p85pb0pk053oa.apps.googleusercontent.com",
              "client_type": 3
            }
          ]
        }
      }
    }
  ],
  "configuration_version": "1"
}